tree_sitter_jinja3_inline-0.8.0.dist-info/RECORD
tree_sitter_jinja3_inline-0.8.0.dist-info/WHEEL
tree_sitter_jinja3_inline-0.8.0.dist-info/top_level.txt
tree_sitter_jinja3_inline-0.8.0.dist-info/METADATA
tree_sitter_jinja_inline/__init__.pyi
tree_sitter_jinja_inline/binding.c
tree_sitter_jinja_inline/__init__.py
tree_sitter_jinja_inline/py.typed
tree_sitter_jinja_inline/_binding.abi3.so
tree_sitter_jinja_inline/queries/highlights.scm
