Metadata-Version: 2.1
Name: tree-sitter-jinja3_inline
Version: 0.8.0
Summary: JinjaInline grammar for tree-sitter
License: MIT
Project-URL: Homepage, https://github.com/tree-sitter/tree-sitter-jinja-inline
Keywords: incremental,parsing,tree-sitter,jinja-inline
Classifier: Intended Audience :: Developers
Classifier: License :: OSI Approved :: MIT License
Classifier: Topic :: Software Development :: Compilers
Classifier: Topic :: Text Processing :: Linguistic
Classifier: Typing :: Typed
Requires-Python: >=3.8
Provides-Extra: core
Requires-Dist: tree-sitter~=0.21; extra == "core"
